pynccl/__init__.py
pynccl/api.py
pynccl/binding.py
pynccl/utils/__init__.py
pynccl/utils/cctypes.py
pynccl/utils/finalizer.py
pynccl/utils/libutils.py
pynccl-0.1.2.dist-info/LICENSE
pynccl-0.1.2.dist-info/METADATA
pynccl-0.1.2.dist-info/WHEEL
pynccl-0.1.2.dist-info/top_level.txt
pynccl-0.1.2.dist-info/RECORD
