Metadata-Version: 2.1
Name: pynccl
Version: 0.1.2
Summary: pynccl - python bindings for NVIDIA NCCL libraries
Home-page: https://github.com/lancelee82/pynccl
Author: Lance Lee
Author-email: lancelee82@163.com
License: MIT License
Platform: UNKNOWN
Classifier: Programming Language :: Python :: 3
Classifier: License :: OSI Approved :: MIT License
Classifier: Operating System :: OS Independent
Classifier: Topic :: Software Development :: Libraries :: Python Modules
Requires-Dist: numpy
Requires-Dist: numba
